HISTORY.rst
LICENSE
MANIFEST.in
README.rst
setup.cfg
setup.py
butterdb/__init__.py
butterdb/butterdb.py
butterdb.egg-info/PKG-INFO
butterdb.egg-info/SOURCES.txt
butterdb.egg-info/dependency_links.txt
butterdb.egg-info/not-zip-safe
butterdb.egg-info/requires.txt
butterdb.egg-info/top_level.txt