Metadata-Version: 1.1
Name: butterdb
Version: 0.1.5
Summary: butterdb is a Python ORM for Google Drive Spreadsheets.
Home-page: https://github.com/Widdershin/butterdb
Author: Nick Johnstone
Author-email: ncwjohnstone@gmail.com
License: MIT
Keywords: butterdb
Platform: UNKNOWN
Classifier: Development Status :: 2 - Pre-Alpha
Classifier: Intended Audience :: Developers
Classifier: Natural Language :: English
Classifier: Programming Language :: Python :: 2
Classifier: Programming Language :: Python :: 2.6
Classifier: Programming Language :: Python :: 2.7
